LICENSE
MANIFEST.in
README.md
requirements.txt
setup.py
bin/carto-print
carto/__init__.py
carto/print.py
carto_print.egg-info/PKG-INFO
carto_print.egg-info/SOURCES.txt
carto_print.egg-info/dependency_links.txt
carto_print.egg-info/requires.txt
carto_print.egg-info/top_level.txt