Metadata-Version: 1.0
Name: carto-print
Version: 0.0.5
Summary: A module to export images from CARTO named maps
Home-page: https://github.com/CartoDB/carto-print
Author: Alberto Romeu
Author-email: alrocar@carto.com
License: UNKNOWN
Platform: UNKNOWN
